lilies/__init__.py
lilies/__main__.py
lilies/base_utils.py
lilies/manage.py
lilies/api/__init__.py
lilies/api/borders.py
lilies/api/columnify.py
lilies/api/grow.py
lilies/api/highlight.py
lilies/api/resize.py
lilies/api/sortify.py
lilies/compiler/__init__.py
lilies/compiler/compiler.py
lilies/compiler/state_manager.py
lilies/objects/__init__.py
lilies/objects/base.py
lilies/objects/lilyblock.py
lilies/objects/lilystring.py
lilies/style/__init__.py
lilies/style/colors.py
lilies/style/palette.py
lilies/style/parse.py
lilies/style/styles.py
lilies/style/palettes/__init__.py
lilies/style/palettes/default.json
lilies/terminal/__init__.py
lilies/terminal/aixterm.py
lilies/terminal/ansi16.py
lilies/terminal/ansi256.py
lilies/terminal/ansi8.py
lilies/terminal/ansi8open.py
lilies/terminal/ansicodes.py
lilies/terminal/attr_mixin.py
lilies/terminal/base.py
lilies/terminal/detect.py
lilies/terminal/exceptions.py
lilies/terminal/nocolor.py
lilies/terminal/truecolor.py
lilies/terminal/win10mixin.py
lilies/terminal/win32mixin.py
lilies/terminal/windows.py
test/__init__.py
test/api/__init__.py
test/api/test_bordered.py
test/api/test_columnify.py
test/api/test_highlight.py
test/api/test_resize.py
lilies-0.3.2.dist-info/LICENSE
lilies-0.3.2.dist-info/METADATA
lilies-0.3.2.dist-info/WHEEL
lilies-0.3.2.dist-info/top_level.txt
lilies-0.3.2.dist-info/RECORD
