Metadata-Version: 2.1
Name: lilies
Version: 0.3.2
Summary: A tool for creating colorful, formatted command line output
Home-page: https://github.com/mrz1988/lilies
Author: Matt Zychowski
Author-email: mrz2004@gmail.com
License: MIT
Platform: UNKNOWN
Requires-Python: >=3.5
Requires-Dist: colorama
Requires-Dist: future
Requires-Dist: importlib-resources ; python_version < "3.7"
